sosecrets/__init__.py
sosecrets/secretdicts.py
sosecrets/secrets.pyi
sosecrets-0.1.12.dist-info/LICENSE
sosecrets-0.1.12.dist-info/METADATA
sosecrets-0.1.12.dist-info/WHEEL
sosecrets-0.1.12.dist-info/RECORD
