Metadata-Version: 2.1
Name: sosecrets
Version: 0.1.12
Summary: Simple wrapper to secure your secrets.
License: MIT
Keywords: secrets,security
Author: Jim Chng
Author-email: jimchng@outlook.com
Requires-Python: >=3.8,<4.0
Classifier: License :: OSI Approved :: MIT License
Classifier: Programming Language :: Python :: 3
Classifier: Programming Language :: Python :: 3.8
Classifier: Programming Language :: Python :: 3.9
Classifier: Programming Language :: Python :: 3.10
Classifier: Programming Language :: Python :: 3.11
Requires-Dist: sosecrets-core (==1.0.20)
